[
  {
    "id": "welcome-to-the-stacks",
    "title": "welcome to the Nayan's Blog",
    "channel": "general",
    "date": "2026-07-15",
    "excerpt": "today it was built."
  },
  {
    "id": "i-start-today-mrl488vm",
    "title": "I start today",
    "channel": "360-360",
    "date": "2026-07-14",
    "excerpt": "...."
  },
  {
    "id": "update-mrlvps9r",
    "title": "UPDATE",
    "channel": "360-360",
    "date": "2026-07-15",
    "excerpt": "TODAY I made full strategy to complete it and score full alongside my other projects and just studying 5 hrs/ day ."
  },
  {
    "id": "working-on-a-article-presenting-a-new-problem-in-game-theory-mrlvwmus",
    "title": "working on a article presenting a new problem in game theory",
    "channel": "general",
    "date": "2026-07-15",
    "excerpt": "i think of naming it predator prey problem"
  },
  {
    "id": "the-almanack-of-naval-ravikant-mrlw2ane",
    "title": "The Almanack of Naval Ravikant",
    "channel": "book-club",
    "date": "2026-07-15",
    "excerpt": "definitely a classic , not completed yet . Rereading the happiness chapter again and again"
  }
]
